[
  {
    "question": "Which option applies in Québec practice? A quality assurance plan’s main purpose is to: (compliance)",
    "choices": [
      "Increase taxes",
      "Replace the contract",
      "Cut documentation",
      "Describe controls to ensure requirements are met"
    ],
    "answer": 3
  },
  {
    "question": "Select the TRUE statement: O&M manuals are typically delivered: (compliance)",
    "choices": [
      "With the bid bond",
      "After warranty expiry",
      "At tender closing",
      "At substantial completion or project closeout"
    ],
    "answer": 3
  },
  {
    "question": "Closeout documents often include:",
    "choices": [
      "Timesheets only",
      "As-builts, O&M manuals, warranties, training records",
      "Only RFIs",
      "Change orders only"
    ],
    "answer": 1
  },
  {
    "question": "Which option applies in Québec practice? A quality assurance plan’s main purpose is to: (compliance)",
    "choices": [
      "Increase taxes",
      "Cut documentation",
      "Describe controls to ensure requirements are met",
      "Replace the contract"
    ],
    "answer": 2
  },
  {
    "question": "Which statement is MOST accurate? In Québec construction, the statutory holdback (retenue) is typically: (Quebec)",
    "choices": [
      "No holdback exists",
      "10% of the value of the work until lien period expiry",
      "1% until final payment",
      "15% for materials only"
    ],
    "answer": 1
  },
  {
    "question": "Working at heights in Québec usually requires:",
    "choices": [
      "Forklift training only",
      "Fall protection training and appropriate equipment",
      "No training",
      "Confined space ticket only"
    ],
    "answer": 1
  },
  {
    "question": "Which statement is MOST accurate? Builder’s Risk (course of construction) insurance mainly covers: (Quebec)",
    "choices": [
      "Worker injuries",
      "Damage to the work under construction",
      "Vehicle collisions",
      "Professional liability"
    ],
    "answer": 1
  },
  {
    "question": "Select the TRUE statement: A quality assurance plan’s main purpose is to: (practice)",
    "choices": [
      "Describe controls to ensure requirements are met",
      "Cut documentation",
      "Increase taxes",
      "Replace the contract"
    ],
    "answer": 0
  },
  {
    "question": "Which option applies in Québec practice? Small consumable tools are best coded to: (compliance)",
    "choices": [
      "Overhead/indirect costs",
      "Accounts receivable",
      "Revenue",
      "Direct materials"
    ],
    "answer": 0
  },
  {
    "question": "Select the TRUE statement: The critical path in a schedule is: (practice)",
    "choices": [
      "A budget contingency",
      "The shortest path",
      "A path with no float because it is ignored",
      "The longest path of dependent tasks determining project duration"
    ],
    "answer": 3
  },
  {
    "question": "Which statement is MOST accurate? When drawings and specifications conflict (and no priority is stated), what is commonly consulted first? (compliance)",
    "choices": [
      "Shop drawings",
      "Verbal instructions",
      "Invoices",
      "Specifications typically take precedence"
    ],
    "answer": 3
  },
  {
    "question": "A method statement / work procedure helps by:",
    "choices": [
      "Defining step-by-step execution and controls for quality and safety",
      "Replacing fall protection",
      "Setting bid prices",
      "Collecting taxes"
    ],
    "answer": 0
  },
  {
    "question": "Which statement is MOST accurate? What is the primary role of the RBQ (Régie du bâtiment du Québec)? (Quebec)",
    "choices": [
      "Regulate construction, building safety, and certain professional qualifications",
      "Set provincial income tax rates",
      "Issue municipal building permits",
      "Manage highway construction contracts"
    ],
    "answer": 0
  },
  {
    "question": "Which statement is MOST accurate? Closeout documents often include: (practice)",
    "choices": [
      "As-builts, O&M manuals, warranties, training records",
      "Change orders only",
      "Timesheets only",
      "Only RFIs"
    ],
    "answer": 0
  },
  {
    "question": "Which option applies in Québec practice? GST and QST on construction invoices in Québec are respectively: (Quebec)",
    "choices": [
      "10% and 5%",
      "No taxes apply",
      "5% and 9.975%",
      "15% combined HST"
    ],
    "answer": 2
  },
  {
    "question": "Which statement is MOST accurate? Which procurement method focuses more on qualifications than price? (Quebec)",
    "choices": [
      "Lowest compliant bid",
      "Reverse auction",
      "Qualifications‑Based Selection (QBS)",
      "Coin toss"
    ],
    "answer": 2
  },
  {
    "question": "Select the TRUE statement: The legal construction hypothec (lien) primarily protects: (Quebec)",
    "choices": [
      "Those who supplied work or materials and remain unpaid",
      "Only banks",
      "Designers’ copyright",
      "Only owners"
    ],
    "answer": 0
  },
  {
    "question": "Which option applies in Québec practice? Commercial General Liability (CGL) insurance covers: (Quebec)",
    "choices": [
      "Only employee wages",
      "Only tool theft",
      "Third-party bodily injury and property damage claims",
      "Only design errors"
    ],
    "answer": 2
  },
  {
    "question": "Which option applies in Québec practice? Corporate directors in Québec have a duty to: (compliance)",
    "choices": [
      "Report only to employees",
      "Act with diligence and oversee the corporation’s affairs",
      "Ignore financial statements",
      "Set municipal bylaws"
    ],
    "answer": 1
  },
  {
    "question": "Which statement is MOST accurate? If the guarantor leaves the company, the contractor must: (Quebec)",
    "choices": [
      "Replace the guarantor within RBQ’s prescribed delay to maintain the licence",
      "Do nothing",
      "Return the licence permanently",
      "Notify the municipality only"
    ],
    "answer": 0
  },
  {
    "question": "O&M manuals are typically delivered:",
    "choices": [
      "At tender closing",
      "At substantial completion or project closeout",
      "After warranty expiry",
      "With the bid bond"
    ],
    "answer": 1
  },
  {
    "question": "Which option applies in Québec practice? A method statement / work procedure helps by: (practice)",
    "choices": [
      "Setting bid prices",
      "Defining step-by-step execution and controls for quality and safety",
      "Replacing fall protection",
      "Collecting taxes"
    ],
    "answer": 1
  },
  {
    "question": "A change directive (directive de changement) differs from a change order because:",
    "choices": [
      "It is unilateral to proceed before price agreement, subject to later valuation",
      "It always reduces scope",
      "It applies only to design-build contracts",
      "It cannot adjust schedule"
    ],
    "answer": 0
  },
  {
    "question": "Which register tracks ownership of shares?",
    "choices": [
      "Asset register",
      "Securities (share) register",
      "RFI log",
      "Accident register"
    ],
    "answer": 1
  },
  {
    "question": "Select the TRUE statement: SIMDUT (WHMIS 2015) primarily concerns: (Quebec)",
    "choices": [
      "Hazardous product classification, labels, and Safety Data Sheets",
      "Corporate governance",
      "Traffic control plans",
      "Income tax filings"
    ],
    "answer": 0
  },
  {
    "question": "Select the TRUE statement: If the guarantor leaves the company, the contractor must: (Quebec)",
    "choices": [
      "Replace the guarantor within RBQ’s prescribed delay to maintain the licence",
      "Return the licence permanently",
      "Do nothing",
      "Notify the municipality only"
    ],
    "answer": 0
  },
  {
    "question": "Which option applies in Québec practice? A minute book primarily contains: (practice)",
    "choices": [
      "Daily site diaries",
      "Invoices only",
      "Safety Data Sheets",
      "Corporate resolutions, director/shareholder records, and by-laws"
    ],
    "answer": 3
  },
  {
    "question": "Which option applies in Québec practice? Which procurement method focuses more on qualifications than price? (practice)",
    "choices": [
      "Reverse auction",
      "Lowest compliant bid",
      "Coin toss",
      "Qualifications‑Based Selection (QBS)"
    ],
    "answer": 3
  },
  {
    "question": "Lockout/Tagout (cadenassage) procedures are used to:",
    "choices": [
      "Decorate equipment",
      "Prevent startup of machinery during maintenance",
      "Speed up production",
      "Replace PPE"
    ],
    "answer": 1
  },
  {
    "question": "Which statement is MOST accurate? Builder’s Risk (course of construction) insurance mainly covers: (Quebec)",
    "choices": [
      "Vehicle collisions",
      "Professional liability",
      "Damage to the work under construction",
      "Worker injuries"
    ],
    "answer": 2
  },
  {
    "question": "Which option applies in Québec practice? A cost contingency in estimates is intended to: (practice)",
    "choices": [
      "Pay taxes",
      "Cover identified risks/uncertainties within scope",
      "Increase profit arbitrarily",
      "Buy tools for employees"
    ],
    "answer": 1
  },
  {
    "question": "Which statement is MOST accurate? Which procurement method focuses more on qualifications than price? (compliance)",
    "choices": [
      "Lowest compliant bid",
      "Qualifications‑Based Selection (QBS)",
      "Reverse auction",
      "Coin toss"
    ],
    "answer": 1
  },
  {
    "question": "Which statement is MOST accurate? A minute book primarily contains: (compliance)",
    "choices": [
      "Corporate resolutions, director/shareholder records, and by-laws",
      "Invoices only",
      "Safety Data Sheets",
      "Daily site diaries"
    ],
    "answer": 0
  },
  {
    "question": "Select the TRUE statement: In Québec construction, the statutory holdback (retenue) is typically: (compliance)",
    "choices": [
      "1% until final payment",
      "10% of the value of the work until lien period expiry",
      "15% for materials only",
      "No holdback exists"
    ],
    "answer": 1
  },
  {
    "question": "Which statement is MOST accurate? Builder’s Risk (course of construction) insurance mainly covers: (Quebec)",
    "choices": [
      "Worker injuries",
      "Damage to the work under construction",
      "Professional liability",
      "Vehicle collisions"
    ],
    "answer": 1
  },
  {
    "question": "Which statement is MOST accurate? If the guarantor leaves the company, the contractor must: (Quebec)",
    "choices": [
      "Replace the guarantor within RBQ’s prescribed delay to maintain the licence",
      "Return the licence permanently",
      "Do nothing",
      "Notify the municipality only"
    ],
    "answer": 0
  },
  {
    "question": "Which statement is MOST accurate? The critical path in a schedule is: (Quebec)",
    "choices": [
      "The longest path of dependent tasks determining project duration",
      "The shortest path",
      "A budget contingency",
      "A path with no float because it is ignored"
    ],
    "answer": 0
  },
  {
    "question": "Select the TRUE statement: GST and QST on construction invoices in Québec are respectively: (Quebec)",
    "choices": [
      "15% combined HST",
      "10% and 5%",
      "No taxes apply",
      "5% and 9.975%"
    ],
    "answer": 3
  },
  {
    "question": "Which option applies in Québec practice? Corporate directors in Québec have a duty to: (Quebec)",
    "choices": [
      "Act with diligence and oversee the corporation’s affairs",
      "Report only to employees",
      "Ignore financial statements",
      "Set municipal bylaws"
    ],
    "answer": 0
  },
  {
    "question": "Which option applies in Québec practice? An environmental aspect (ISO 14001) is: (practice)",
    "choices": [
      "A payroll record",
      "A shop drawing",
      "A lawsuit",
      "An element of activities that can interact with the environment"
    ],
    "answer": 3
  },
  {
    "question": "Select the TRUE statement: Concrete compressive strength is verified by: (compliance)",
    "choices": [
      "Torque wrench",
      "Visual inspection",
      "Laboratory cylinder break tests at specified ages",
      "Slump test only"
    ],
    "answer": 2
  },
  {
    "question": "Which option applies in Québec practice? An RFI (request for information) serves to: (compliance)",
    "choices": [
      "Replace shop drawings",
      "Approve progress claims automatically",
      "Modify contract price directly",
      "Clarify discrepancies or request missing information from the designer/owner"
    ],
    "answer": 3
  },
  {
    "question": "Which statement is MOST accurate? The CNESST’s first expectation when a serious accident occurs is to: (compliance)",
    "choices": [
      "Destroy documents",
      "Post on social media",
      "Secure the site, assist the injured, and notify emergency services",
      "Continue work to meet schedule"
    ],
    "answer": 2
  },
  {
    "question": "Which statement is MOST accurate? Shop drawings are primarily: (compliance)",
    "choices": [
      "Owner’s financing documents",
      "Contract documents",
      "Contractor/submittal documents showing how work will be fabricated/installed",
      "Legal filings with AMP"
    ],
    "answer": 2
  },
  {
    "question": "Which statement is MOST accurate? The legal construction hypothec (lien) primarily protects: (Quebec)",
    "choices": [
      "Designers’ copyright",
      "Only banks",
      "Only owners",
      "Those who supplied work or materials and remain unpaid"
    ],
    "answer": 3
  },
  {
    "question": "An RFI (request for information) serves to:",
    "choices": [
      "Replace shop drawings",
      "Clarify discrepancies or request missing information from the designer/owner",
      "Approve progress claims automatically",
      "Modify contract price directly"
    ],
    "answer": 1
  },
  {
    "question": "Select the TRUE statement: The CCQ (Commission de la construction du Québec) primarily: (practice)",
    "choices": [
      "Issues building permits",
      "Administers collective agreements and labour relations in the construction industry",
      "Collects municipal taxes",
      "Manages health inspections in restaurants"
    ],
    "answer": 1
  },
  {
    "question": "Which option applies in Québec practice? An input tax credit (ITC) allows a registrant to: (Quebec)",
    "choices": [
      "Avoid corporate taxes",
      "Refund employees’ personal taxes",
      "Recover eligible GST/QST paid on business inputs",
      "Increase sales tax collected"
    ],
    "answer": 2
  },
  {
    "question": "Select the TRUE statement: Baseline schedule updates should occur: (compliance)",
    "choices": [
      "Never",
      "Only at project end",
      "Only through formal change control",
      "Daily without record"
    ],
    "answer": 2
  },
  {
    "question": "Select the TRUE statement: Baseline schedule updates should occur: (practice)",
    "choices": [
      "Only through formal change control",
      "Daily without record",
      "Only at project end",
      "Never"
    ],
    "answer": 0
  }
]